spydbpy/__init__.py
spydbpy-0.0.2.dist-info/METADATA
spydbpy-0.0.2.dist-info/WHEEL
spydbpy-0.0.2.dist-info/top_level.txt
spydbpy-0.0.2.dist-info/RECORD
