Metadata-Version: 2.4
Name: spydbpy
Version: 0.0.2
Summary: A Python library to interact with SborgDB API.
Author-email: Your Name <your.email@example.com>
Classifier: Programming Language :: Python :: 3
Classifier: License :: OSI Approved :: MIT License
Classifier: Operating System :: OS Independent
Requires-Python: >=3.6
Requires-Dist: requests
